moxn/__init__.py
moxn/client.py
moxn/generator.py
moxn/py.typed
moxn/settings.py
moxn/base_models/__init__.py
moxn/base_models/content_block.py
moxn/base_models/blocks/base.py
moxn/base_models/blocks/context.py
moxn/base_models/blocks/file.py
moxn/base_models/blocks/image.py
moxn/base_models/blocks/signed.py
moxn/base_models/blocks/text.py
moxn/base_models/blocks/tool.py
moxn/base_models/blocks/variable.py
moxn/base_models/providers/anthropic.py
moxn/base_models/providers/base.py
moxn/base_models/providers/google_gemini.py
moxn/base_models/providers/google_vertex.py
moxn/base_models/providers/openai_chat.py
moxn/base_models/providers/openai_responses.py
moxn/base_models/providers/utils.py
moxn/base_models/reducers/reducer_document.py
moxn/base_models/reducers/reducer_inline_variable.py
moxn/content/backend.py
moxn/content/client.py
moxn/content/engine.py
moxn/content/models.py
moxn/models/__init__.py
moxn/models/message.py
moxn/models/response.py
moxn/models/schema.py
moxn/models/task.py
moxn/models/prompt/__init__.py
moxn/models/prompt/content.py
moxn/models/prompt/conversion.py
moxn/models/prompt/core.py
moxn/models/prompt/prompt_converter.py
moxn/models/prompt/response_handler.py
moxn/models/prompt/session.py
moxn/models/prompt/structured_output.py
moxn/models/prompt/tool_formatter.py
moxn/schema_generator/__init__.py
moxn/schema_generator/generator.py
moxn/storage/__init__.py
moxn/storage/base.py
moxn/storage/storage.py
moxn/telemetry/__init__.py
moxn/telemetry/backend.py
moxn/telemetry/client.py
moxn/telemetry/context.py
moxn/telemetry/dispatcher.py
moxn/telemetry/metrics.py
moxn/types/__init__.py
moxn/types/auth.py
moxn/types/base.py
moxn/types/content.py
moxn/types/dto.py
moxn/types/exceptions.py
moxn/types/py.typed
moxn/types/request_config.py
moxn/types/requests.py
moxn/types/response.py
moxn/types/responses.py
moxn/types/schema.py
moxn/types/sentinel.py
moxn/types/studio.py
moxn/types/telemetry.py
moxn/types/tool.py
moxn/types/utils.py
moxn-0.0.20.dist-info/METADATA
moxn-0.0.20.dist-info/WHEEL
moxn-0.0.20.dist-info/RECORD
